README.md
setup.cfg
setup.py
distributions424242/Binomialdistribution.py
distributions424242/Gaussiandistribution.py
distributions424242/Generaldistribution.py
distributions424242/__init__.py
distributions424242.egg-info/PKG-INFO
distributions424242.egg-info/SOURCES.txt
distributions424242.egg-info/dependency_links.txt
distributions424242.egg-info/not-zip-safe
distributions424242.egg-info/top_level.txt